odoo/addons/stock_quant_cost_info/README.rst
odoo/addons/stock_quant_cost_info/__init__.py
odoo/addons/stock_quant_cost_info/__manifest__.py
odoo/addons/stock_quant_cost_info/hooks.py
odoo/addons/stock_quant_cost_info/i18n/es.po
odoo/addons/stock_quant_cost_info/i18n/it.po
odoo/addons/stock_quant_cost_info/i18n/stock_quant_cost_info.pot
odoo/addons/stock_quant_cost_info/models/__init__.py
odoo/addons/stock_quant_cost_info/models/stock_quant.py
odoo/addons/stock_quant_cost_info/readme/CONTRIBUTORS.md
odoo/addons/stock_quant_cost_info/readme/DESCRIPTION.md
odoo/addons/stock_quant_cost_info/readme/INSTALL.md
odoo/addons/stock_quant_cost_info/readme/USAGE.md
odoo/addons/stock_quant_cost_info/static/description/icon.png
odoo/addons/stock_quant_cost_info/static/description/index.html
odoo/addons/stock_quant_cost_info/tests/__init__.py
odoo/addons/stock_quant_cost_info/tests/test_stock_quant_cost_info.py
odoo/addons/stock_quant_cost_info/views/report_stockinventory.xml
odoo/addons/stock_quant_cost_info/views/stock_inventory_views.xml
odoo_addon_stock_quant_cost_info-18.0.1.0.0.7.dist-info/METADATA
odoo_addon_stock_quant_cost_info-18.0.1.0.0.7.dist-info/WHEEL
odoo_addon_stock_quant_cost_info-18.0.1.0.0.7.dist-info/top_level.txt
odoo_addon_stock_quant_cost_info-18.0.1.0.0.7.dist-info/RECORD
